{
    "object_alias": "exface.Core.PAGE_GROUP",
    "columns": [
        {
            "name": "CREATED_ON",
            "attribute_alias": "CREATED_ON"
        },
        {
            "name": "MODIFIED_ON",
            "attribute_alias": "MODIFIED_ON"
        },
        {
            "name": "CREATED_BY_USER",
            "attribute_alias": "CREATED_BY_USER"
        },
        {
            "name": "MODIFIED_BY_USER",
            "attribute_alias": "MODIFIED_BY_USER"
        },
        {
            "name": "UID",
            "attribute_alias": "UID"
        },
        {
            "name": "NAME",
            "attribute_alias": "NAME"
        },
        {
            "name": "APP",
            "attribute_alias": "APP"
        },
        {
            "name": "DESCRIPTION",
            "attribute_alias": "DESCRIPTION"
        }
    ],
    "rows": [
        {
            "CREATED_ON": "2024-03-22 13:45:26",
            "MODIFIED_ON": "2024-03-22 13:46:00",
            "CREATED_BY_USER": "0x11ebb7e1d97b26d6b7e1005056bee7c0",
            "MODIFIED_BY_USER": "0x11ebb7e1d97b26d6b7e1005056bee7c0",
            "UID": "0x11ee80430e9aebca8043005056be9fa0",
            "NAME": "Testing",
            "APP": "0x38000000000000000000000000000000",
            "DESCRIPTION": "Pages for Testers"
        }
    ],
    "totals_rows": [],
    "filters": {
        "operator": "AND",
        "base_object_alias": "exface.Core.PAGE_GROUP",
        "conditions": [
            {
                "expression": "APP",
                "comparator": "=",
                "value": "0x38000000000000000000000000000000",
                "object_alias": "exface.Core.PAGE_GROUP"
            }
        ]
    },
    "rows_limit": null,
    "rows_offset": 0,
    "sorters": [
        {
            "attribute_alias": "CREATED_ON",
            "direction": "ASC"
        },
        {
            "attribute_alias": "UID",
            "direction": "ASC"
        }
    ]
}